min_cart/__init__.py
min_cart/apps/__init__.py
min_cart/apps/cart/__init__.py
min_cart/apps/cart/apps.py
min_cart/apps/cart/graphql/__init__.py
min_cart/apps/cart/graphql/cart.py
min_cart/apps/cart/graphql/schema.py
min_cart/apps/cart/models.py
min_cart/schema.py
min_cart-0.1.5.dist-info/METADATA
min_cart-0.1.5.dist-info/WHEEL
min_cart-0.1.5.dist-info/RECORD
