Metadata-Version: 2.1
Name: min-cart
Version: 0.1.5
Summary: 
Author: ygagjunais
Author-email: junais@yougotagift.com
Requires-Python: >=3.8,<4.0
Classifier: Programming Language :: Python :: 3
Classifier: Programming Language :: Python :: 3.8
Classifier: Programming Language :: Python :: 3.9
Classifier: Programming Language :: Python :: 3.10
Classifier: Programming Language :: Python :: 3.11
Requires-Dist: django (>=3.2,<4.0)
Requires-Dist: django-graphql-jwt (==0.3.4)
Requires-Dist: graphene (==3.0)
Requires-Dist: graphene-django (==3.0.0b7)
Requires-Dist: graphql-core (==3.1.7)
Requires-Dist: graphql-relay (==3.1.5)
